{"title":"Problem Set 7 - Solutions","markdown":{"yaml":{"title":"Problem Set 7 - Solutions","subtitle":"Economics 100B - Intermediate Microeconomic Theory\nProf. Muehlegger\n","author":"Prof. Muehlegger","format":{"pdf":"default","html":"default"}},"headingText":"Question 1: Risk and Uncertainty","containsRefs":false,"markdown":"\n\n\nConsider the following uncertain event. An investor can choose between three options:\n\n    -    A safe investment that is worth $2500 with certainty.\n    -    A risky investment that is worth $40,000 with probability 10%, and $0 with probability 90%\n    -    A diversified investment that is worth $10,000 with probability 30%, and $0 with probability 70%\n\n(a) (a) Which of the following options has the highest expected value? What does that tell us about the\n    preferences for a risk-neutral investor?\n\nThe expected values are:\n\nSafe investment -- $2,500\n\nRisky investment -- $40k * 10% + $0 * 90% = $4,000\n\nDiversified investment -- $10k * 30% + $0 * 70% = $3,000\n\nThe risky investment has the highest expected value. Since the risky investment offers the highest expected\nvalue, it would be the option preferred by a risk-neutral investor.\n\n(b) Can you conclude anything from part (a) about which option a risk-seeking investor would prefer?\n    Briefly explain.\n\nYes. A risk-seeking investor would tend to like the riskier options even more than the risk-neutral investor.\nSo, in this case, if the risk-neutral investor prefers the riskiest option, a risk-seeking investor would have an\neven stronger preference for the riskiest option.\n\n(c) Suppose that the investor has a utility for wealth given by U(W) = √W. What does that utility function\n    tell us about the investor’s preference for risk? Briefly describe your answer.\n\nSince U(W) is increasing but concave, this tells us that the investor is risk-averse.\n\n(d) Given the investor’s utility function from part (b), which investment maximizes expected utility?\n\nThe expected utilities are:\n\nSafe investment – sqrt(2500) = 50.\n\nRisky investment -- sqrt(40k) * 10% + sqrt(0) * 90% = 200 * 10% = 20\n\nDiversified investment -- sqrt(10k) * 30% + sqrt(0) * 70% = 100 * 30% = 30\n\nThe safe investment has the highest expected value.\n\n(e) Given the investor’s utility function from part (b), what is the certainty equivalent for each of the three\n    investments? (i.e., the certain amount that would yield similar utility)?\n\nSince U(W) = √W, the certainty equivalent of each can be found by squaring the expected utility of each of\nthe risky investments.\n\nThe certainty equivalents are:\n\nSafe investment – $2,500.\n\nRisky investment -- $400\n\nDiversified investment -- $900\n\n(f) How much would the probability that the risky investment is worth $40,000 have to be in order for the\n    risk averse investor to be indifferent between the risky investment and the option in part (d) that\n    maximizes his or her expected utility?\n\nLet’s use the variable p to denote the probability of success for the risky investment. We can write the\nexpected utility of the risky investment as:\n\n$EU of Risky investment -- sqrt(40k) * p + sqrt(0) * (1-p) = 200 * p.$\n\nThe option in part (d) that the risk-neutral investor preferred (i.e., the safe investment) generated an\nexpected utility of 50.\n\nTherefore, the risk-averse investor would be indifferent between the safe investment and the risky\ninvestment if the expected utility of the risky investment also generated 50 units of utility.\n\nEU of Risky investment: $200p = 50 \\Rightarrow p = \\frac{1}{4}$. If the probability of success of the risky investment is\n25%, the risk averse investor would be indifferent between the risky and safe investments.\n\n## Question 2: Mitigating Risk\n\nThe NBA finals feature the Denver Nuggets and the Miami Heat. A manufacturer has two choices:\n\n    1.   Produce shirts and souvenirs for Denver. This is worth $10,000 if Denver wins and $900 if\n         Denver loses.\n    2.   Produce shirts and souvenirs for Miami. This is worth $10,000 if Miami wins and $900 if Miami\n         loses.\n\n    3.   Produce shirts and souvenirs for UC Davis: This is worth $3600 regardless of the outcome of the\n         NBA finals.\n\nSuppose that the probability that Denver wins is 60%.\n\n    (a) Calculate expected value for each of the three options. What choice would a risk-neutral\n        manufacturer make?\n\n         The expected value (EV) is calculated as follows: $EV = \\sum_i (\\Pr_i \\cdot V_i)$ (Probability of\n         Outcome i).\n\n         Denver Nuggets:\n\n         EV = (0.60 * $10,000) + (0.40 * $900) = $6,000 + $360 = $6,360\n\n         Miami Heat:\n\n         Since the probability that Denver wins is 60%, the probability that Miami wins is 40%.\n\n         EV = (0.40 * $10,000) + (0.60 * $900) = $4,000 + $540 = $4,540\n\n         UC Davis:\n\n         The outcome is certain, so the EV is just the guaranteed amount.\n\n         EV = $3,600\n\n         A risk-neutral manufacturer is indifferent to risk. Therefore, they would choose the option with the\n         highest expected value, which in this case would be to produce shirts and souvenirs for the Denver\n         Nuggets, as it has the highest expected value ($6,360).\n\n    (b) Suppose that next door to the manufacturer, there is fortune teller who can perfectly predict who\n        will win the NBA finals. If the fortune tells the factory owner that they can predict the winner for\n        $2500, is it worth it to the risk-neutral factory owner to pay? What is the most that the\n        manufacturer would be willing to pay?\n\n         If the fortune teller can predict the NBA finals' winner with perfect accuracy, the manufacturer\n         would be guaranteed a payoff of $10,000 (since they can choose the winning team). If the fortune\n         teller charges $2,500 for this information, the manufacturer's net gain would be:\n\n         $10,000 - $2,500 = $7,500\n\n         Since $7,500 is more than the maximum expected value without the fortune teller's information\n         ($6,360), it would be worth it for the risk-neutral manufacturer to pay the fortune teller's fee.\n\n         The most the manufacturer should be willing to pay is the difference between the certain payoff\n         from knowing the winning team ($10,000) and the highest expected value without knowing the\n\n    winner ($6,360). This is because paying more would result in an expected profit less than the one\n    expected without the fortune teller's information.\n\n    So, Maximum Payment = $10,000 - $6,360 = $3,640\n\n(c) Now suppose that the manufacturer is risk-averse with a utility function given by U(W) = √W.\n    What is the expected utility of each option? What choice would the risk-averse manufacturer\n    make?\n\n    For a risk-averse manufacturer with utility function U(W) = √W, we will calculate the expected\n    utility (EU) for each option.\n\n    Denver Nuggets:\n\n    EU = (0.60 * √$10,000) + (0.40 * √$900) = 0.60 * 100 + 0.40 * 30 = 60 + 12 = 72\n\n    Miami Heat:\n\n    EU = (0.40 * √$10,000) + (0.60 * √$900) = 0.40 * 100 + 0.60 * 30 = 40 + 18 = 58\n\n    UC Davis:\n\n    EU = √$3,600 = 60\n\n    So, the risk-averse manufacturer would choose to produce shirts and souvenirs for Denver\n    Nuggets as it provides the highest expected utility (72). Here, although UC Davis merchandise is\n    the least risky option, a risk-averse manufacturer still prefers to produce Denver merchandise\n    because of the higher upside.\n\n(d) Did your answer in part (c) change relative to your answer in part (a)? Briefly explain why or why\n    not.\n\n    The answer is the same as in part (a). Both the risk-neutral and risk-averse manufacturers choose\n    to produce for the Denver Nuggets. This is because the Denver Nuggets have the highest\n    probability of winning, so their expected value and expected utility are both the highest among the\n    options.\n\n    However, the rationale differs between risk-neutral and risk-averse manufacturers. The risk-\n    neutral manufacturer maximizes expected monetary value, while the risk-averse manufacturer\n    maximizes expected utility, considering their aversion to risk.\n\n(e) Finally, suppose the manufacturer could choose to split production and produce some items for\n    Denver and some items for Miami. The items for the winning team are worth $5,000 and the\n    items for the losing team are worth $450. Would the risk-adverse manufacturer prefer this to their\n    choice in part (c)? Briefly explain why or why not.\n\nIn the split production scenario, the payoff is guaranteed to be $5,000 (for the winner) and $450\n(for the loser), regardless of which team wins.\n\nThe utility of this option is: U = √$5,450 = 73.81 (approx)\n\nComparing this to the choice in part (c), this new expected utility (73.81) is higher than the\nexpected utility of producing solely for Denver Nuggets (72). Hence, the risk-averse manufacturer\nwould prefer this option of splitting production between the two teams, because it guarantees a\nhigher utility. The risk is also less because there's no longer a complete loss if one team doesn't\nwin - the manufacturer will still make some profit from the losing team's merchandise. This aligns\nwith their risk-averse behavior.\n\nThis is a form of diversification – the outcomes for Denver and Miami are perfectly negatively\ncorrelated, so by making \\frac{1}{2} Denver and \\frac{1}{2} Miami merchandise, the manufacturer can completely\nmitigate risk.\n\n\n\n\n\n","srcMarkdownNoYaml":"\n\n## Question 1: Risk and Uncertainty\n\nConsider the following uncertain event. An investor can choose between three options:\n\n    -    A safe investment that is worth $2500 with certainty.\n    -    A risky investment that is worth $40,000 with probability 10%, and $0 with probability 90%\n    -    A diversified investment that is worth $10,000 with probability 30%, and $0 with probability 70%\n\n(a) (a) Which of the following options has the highest expected value? What does that tell us about the\n    preferences for a risk-neutral investor?\n\nThe expected values are:\n\nSafe investment -- $2,500\n\nRisky investment -- $40k * 10% + $0 * 90% = $4,000\n\nDiversified investment -- $10k * 30% + $0 * 70% = $3,000\n\nThe risky investment has the highest expected value. Since the risky investment offers the highest expected\nvalue, it would be the option preferred by a risk-neutral investor.\n\n(b) Can you conclude anything from part (a) about which option a risk-seeking investor would prefer?\n    Briefly explain.\n\nYes. A risk-seeking investor would tend to like the riskier options even more than the risk-neutral investor.\nSo, in this case, if the risk-neutral investor prefers the riskiest option, a risk-seeking investor would have an\neven stronger preference for the riskiest option.\n\n(c) Suppose that the investor has a utility for wealth given by U(W) = √W. What does that utility function\n    tell us about the investor’s preference for risk? Briefly describe your answer.\n\nSince U(W) is increasing but concave, this tells us that the investor is risk-averse.\n\n(d) Given the investor’s utility function from part (b), which investment maximizes expected utility?\n\nThe expected utilities are:\n\nSafe investment – sqrt(2500) = 50.\n\nRisky investment -- sqrt(40k) * 10% + sqrt(0) * 90% = 200 * 10% = 20\n\nDiversified investment -- sqrt(10k) * 30% + sqrt(0) * 70% = 100 * 30% = 30\n\nThe safe investment has the highest expected value.\n\n(e) Given the investor’s utility function from part (b), what is the certainty equivalent for each of the three\n    investments? (i.e., the certain amount that would yield similar utility)?\n\nSince U(W) = √W, the certainty equivalent of each can be found by squaring the expected utility of each of\nthe risky investments.\n\nThe certainty equivalents are:\n\nSafe investment – $2,500.\n\nRisky investment -- $400\n\nDiversified investment -- $900\n\n(f) How much would the probability that the risky investment is worth $40,000 have to be in order for the\n    risk averse investor to be indifferent between the risky investment and the option in part (d) that\n    maximizes his or her expected utility?\n\nLet’s use the variable p to denote the probability of success for the risky investment. We can write the\nexpected utility of the risky investment as:\n\n$EU of Risky investment -- sqrt(40k) * p + sqrt(0) * (1-p) = 200 * p.$\n\nThe option in part (d) that the risk-neutral investor preferred (i.e., the safe investment) generated an\nexpected utility of 50.\n\nTherefore, the risk-averse investor would be indifferent between the safe investment and the risky\ninvestment if the expected utility of the risky investment also generated 50 units of utility.\n\nEU of Risky investment: $200p = 50 \\Rightarrow p = \\frac{1}{4}$. If the probability of success of the risky investment is\n25%, the risk averse investor would be indifferent between the risky and safe investments.\n\n## Question 2: Mitigating Risk\n\nThe NBA finals feature the Denver Nuggets and the Miami Heat. A manufacturer has two choices:\n\n    1.   Produce shirts and souvenirs for Denver. This is worth $10,000 if Denver wins and $900 if\n         Denver loses.\n    2.   Produce shirts and souvenirs for Miami. This is worth $10,000 if Miami wins and $900 if Miami\n         loses.\n\n    3.   Produce shirts and souvenirs for UC Davis: This is worth $3600 regardless of the outcome of the\n         NBA finals.\n\nSuppose that the probability that Denver wins is 60%.\n\n    (a) Calculate expected value for each of the three options. What choice would a risk-neutral\n        manufacturer make?\n\n         The expected value (EV) is calculated as follows: $EV = \\sum_i (\\Pr_i \\cdot V_i)$ (Probability of\n         Outcome i).\n\n         Denver Nuggets:\n\n         EV = (0.60 * $10,000) + (0.40 * $900) = $6,000 + $360 = $6,360\n\n         Miami Heat:\n\n         Since the probability that Denver wins is 60%, the probability that Miami wins is 40%.\n\n         EV = (0.40 * $10,000) + (0.60 * $900) = $4,000 + $540 = $4,540\n\n         UC Davis:\n\n         The outcome is certain, so the EV is just the guaranteed amount.\n\n         EV = $3,600\n\n         A risk-neutral manufacturer is indifferent to risk. Therefore, they would choose the option with the\n         highest expected value, which in this case would be to produce shirts and souvenirs for the Denver\n         Nuggets, as it has the highest expected value ($6,360).\n\n    (b) Suppose that next door to the manufacturer, there is fortune teller who can perfectly predict who\n        will win the NBA finals. If the fortune tells the factory owner that they can predict the winner for\n        $2500, is it worth it to the risk-neutral factory owner to pay? What is the most that the\n        manufacturer would be willing to pay?\n\n         If the fortune teller can predict the NBA finals' winner with perfect accuracy, the manufacturer\n         would be guaranteed a payoff of $10,000 (since they can choose the winning team). If the fortune\n         teller charges $2,500 for this information, the manufacturer's net gain would be:\n\n         $10,000 - $2,500 = $7,500\n\n         Since $7,500 is more than the maximum expected value without the fortune teller's information\n         ($6,360), it would be worth it for the risk-neutral manufacturer to pay the fortune teller's fee.\n\n         The most the manufacturer should be willing to pay is the difference between the certain payoff\n         from knowing the winning team ($10,000) and the highest expected value without knowing the\n\n    winner ($6,360). This is because paying more would result in an expected profit less than the one\n    expected without the fortune teller's information.\n\n    So, Maximum Payment = $10,000 - $6,360 = $3,640\n\n(c) Now suppose that the manufacturer is risk-averse with a utility function given by U(W) = √W.\n    What is the expected utility of each option? What choice would the risk-averse manufacturer\n    make?\n\n    For a risk-averse manufacturer with utility function U(W) = √W, we will calculate the expected\n    utility (EU) for each option.\n\n    Denver Nuggets:\n\n    EU = (0.60 * √$10,000) + (0.40 * √$900) = 0.60 * 100 + 0.40 * 30 = 60 + 12 = 72\n\n    Miami Heat:\n\n    EU = (0.40 * √$10,000) + (0.60 * √$900) = 0.40 * 100 + 0.60 * 30 = 40 + 18 = 58\n\n    UC Davis:\n\n    EU = √$3,600 = 60\n\n    So, the risk-averse manufacturer would choose to produce shirts and souvenirs for Denver\n    Nuggets as it provides the highest expected utility (72). Here, although UC Davis merchandise is\n    the least risky option, a risk-averse manufacturer still prefers to produce Denver merchandise\n    because of the higher upside.\n\n(d) Did your answer in part (c) change relative to your answer in part (a)? Briefly explain why or why\n    not.\n\n    The answer is the same as in part (a). Both the risk-neutral and risk-averse manufacturers choose\n    to produce for the Denver Nuggets. This is because the Denver Nuggets have the highest\n    probability of winning, so their expected value and expected utility are both the highest among the\n    options.\n\n    However, the rationale differs between risk-neutral and risk-averse manufacturers. The risk-\n    neutral manufacturer maximizes expected monetary value, while the risk-averse manufacturer\n    maximizes expected utility, considering their aversion to risk.\n\n(e) Finally, suppose the manufacturer could choose to split production and produce some items for\n    Denver and some items for Miami. The items for the winning team are worth $5,000 and the\n    items for the losing team are worth $450. Would the risk-adverse manufacturer prefer this to their\n    choice in part (c)? Briefly explain why or why not.\n\nIn the split production scenario, the payoff is guaranteed to be $5,000 (for the winner) and $450\n(for the loser), regardless of which team wins.\n\nThe utility of this option is: U = √$5,450 = 73.81 (approx)\n\nComparing this to the choice in part (c), this new expected utility (73.81) is higher than the\nexpected utility of producing solely for Denver Nuggets (72). Hence, the risk-averse manufacturer\nwould prefer this option of splitting production between the two teams, because it guarantees a\nhigher utility. The risk is also less because there's no longer a complete loss if one team doesn't\nwin - the manufacturer will still make some profit from the losing team's merchandise. This aligns\nwith their risk-averse behavior.\n\nThis is a form of diversification – the outcomes for Denver and Miami are perfectly negatively\ncorrelated, so by making \\frac{1}{2} Denver and \\frac{1}{2} Miami merchandise, the manufacturer can completely\nmitigate risk.\n\n\n\n\n\n"},"formats":{"html":{"identifier":{"display-name":"HTML","target-format":"html","base-format":"html"},"execute":{"fig-width":7,"fig-height":5,"fig-format":"retina","fig-dpi":96,"df-print":"default","error":false,"eval":true,"cache":false,"freeze":false,"echo":false,"output":true,"warning":false,"include":true,"keep-md":false,"keep-ipynb":false,"ipynb":null,"enabled":null,"daemon":null,"daemon-restart":false,"debug":false,"ipynb-filters":[],"ipynb-shell-interactivity":null,"plotly-connected":true,"message":false,"engine":"markdown"},"render":{"keep-tex":false,"keep-typ":false,"keep-source":false,"keep-hidden":false,"prefer-html":false,"output-divs":true,"output-ext":"html","fig-align":"default","fig-pos":null,"fig-env":null,"code-fold":true,"code-overflow":"scroll","code-link":false,"code-line-numbers":false,"code-tools":false,"tbl-colwidths":"auto","merge-includes":true,"inline-includes":false,"preserve-yaml":false,"latex-auto-mk":true,"latex-auto-install":true,"latex-clean":true,"latex-min-runs":1,"latex-max-runs":10,"latex-makeindex":"makeindex","latex-makeindex-opts":[],"latex-tlmgr-opts":[],"latex-input-paths":[],"latex-output-dir":null,"link-external-icon":false,"link-external-newwindow":true,"self-contained-math":false,"format-resources":[],"notebook-links":true},"pandoc":{"standalone":true,"wrap":"none","default-image-extension":"png","to":"html","toc":false,"toc-depth":3,"number-sections":false,"embed-resources":true,"self-contained":true,"html-math-method":"katex","output-file":"ECN100B_PS7_solutions.html"},"language":{"toc-title-document":"Table of contents","toc-title-website":"On this page","related-formats-title":"Other Formats","related-notebooks-title":"Notebooks","source-notebooks-prefix":"Source","other-links-title":"Other Links","code-links-title":"Code Links","launch-dev-container-title":"Launch Dev Container","launch-binder-title":"Launch Binder","article-notebook-label":"Article Notebook","notebook-preview-download":"Download Notebook","notebook-preview-download-src":"Download Source","notebook-preview-back":"Back to Article","manuscript-meca-bundle":"MECA Bundle","section-title-abstract":"Abstract","section-title-appendices":"Appendices","section-title-footnotes":"Footnotes","section-title-references":"References","section-title-reuse":"Reuse","section-title-copyright":"Copyright","section-title-citation":"Citation","appendix-attribution-cite-as":"For attribution, please cite this work as:","appendix-attribution-bibtex":"BibTeX citation:","appendix-view-license":"View License","title-block-author-single":"Author","title-block-author-plural":"Authors","title-block-affiliation-single":"Affiliation","title-block-affiliation-plural":"Affiliations","title-block-published":"Published","title-block-modified":"Modified","title-block-keywords":"Keywords","callout-tip-title":"Tip","callout-note-title":"Note","callout-warning-title":"Warning","callout-important-title":"Important","callout-caution-title":"Caution","code-summary":"Code","code-tools-menu-caption":"Code","code-tools-show-all-code":"Show All Code","code-tools-hide-all-code":"Hide All Code","code-tools-view-source":"View Source","code-tools-source-code":"Source Code","tools-share":"Share","tools-download":"Download","code-line":"Line","code-lines":"Lines","copy-button-tooltip":"Copy to Clipboard","copy-button-tooltip-success":"Copied!","repo-action-links-edit":"Edit this page","repo-action-links-source":"View source","repo-action-links-issue":"Report an issue","back-to-top":"Back to top","search-no-results-text":"No results","search-matching-documents-text":"matching documents","search-copy-link-title":"Copy link to search","search-hide-matches-text":"Hide additional matches","search-more-match-text":"more match in this document","search-more-matches-text":"more matches in this document","search-clear-button-title":"Clear","search-text-placeholder":"","search-detached-cancel-button-title":"Cancel","search-submit-button-title":"Submit","search-label":"Search","toggle-section":"Toggle section","toggle-sidebar":"Toggle sidebar navigation","toggle-dark-mode":"Toggle dark mode","toggle-reader-mode":"Toggle reader mode","toggle-navigation":"Toggle navigation","crossref-fig-title":"Figure","crossref-tbl-title":"Table","crossref-lst-title":"Listing","crossref-thm-title":"Theorem","crossref-lem-title":"Lemma","crossref-cor-title":"Corollary","crossref-prp-title":"Proposition","crossref-cnj-title":"Conjecture","crossref-def-title":"Definition","crossref-exm-title":"Example","crossref-exr-title":"Exercise","crossref-ch-prefix":"Chapter","crossref-apx-prefix":"Appendix","crossref-sec-prefix":"Section","crossref-eq-prefix":"Equation","crossref-lof-title":"List of Figures","crossref-lot-title":"List of Tables","crossref-lol-title":"List of Listings","environment-proof-title":"Proof","environment-remark-title":"Remark","environment-solution-title":"Solution","listing-page-order-by":"Order By","listing-page-order-by-default":"Default","listing-page-order-by-date-asc":"Oldest","listing-page-order-by-date-desc":"Newest","listing-page-order-by-number-desc":"High to Low","listing-page-order-by-number-asc":"Low to High","listing-page-field-date":"Date","listing-page-field-title":"Title","listing-page-field-description":"Description","listing-page-field-author":"Author","listing-page-field-filename":"File Name","listing-page-field-filemodified":"Modified","listing-page-field-subtitle":"Subtitle","listing-page-field-readingtime":"Reading Time","listing-page-field-wordcount":"Word Count","listing-page-field-categories":"Categories","listing-page-minutes-compact":"{0} min","listing-page-category-all":"All","listing-page-no-matches":"No matching items","listing-page-words":"{0} words","listing-page-filter":"Filter","draft":"Draft"},"metadata":{"lang":"en","fig-responsive":true,"quarto-version":"1.8.27","toc-location":"right","anchor-sections":true,"smooth-scroll":false,"theme":"cosmo","fig-cap-location":"bottom","code-copy":true,"citations-hover":false,"crossref":{"fig-title":"Figure","tbl-title":"Table","eq-title":"Equation"}},"extensions":{"book":{"multiFile":true}}},"pdf":{"identifier":{"display-name":"PDF","target-format":"pdf","base-format":"pdf"},"execute":{"fig-width":5.5,"fig-height":3.5,"fig-format":"pdf","fig-dpi":300,"df-print":"default","error":false,"eval":true,"cache":false,"freeze":false,"echo":false,"output":true,"warning":false,"include":true,"keep-md":false,"keep-ipynb":false,"ipynb":null,"enabled":null,"daemon":null,"daemon-restart":false,"debug":false,"ipynb-filters":[],"ipynb-shell-interactivity":null,"plotly-connected":true,"message":false,"engine":"markdown"},"render":{"keep-tex":false,"keep-typ":false,"keep-source":false,"keep-hidden":false,"prefer-html":false,"output-divs":true,"output-ext":"pdf","fig-align":"default","fig-pos":"htbp","fig-env":null,"code-fold":"none","code-overflow":"scroll","code-link":false,"code-line-numbers":false,"code-tools":false,"tbl-colwidths":true,"merge-includes":true,"inline-includes":false,"preserve-yaml":false,"latex-auto-mk":true,"latex-auto-install":true,"latex-clean":true,"latex-min-runs":1,"latex-max-runs":10,"latex-makeindex":"makeindex","latex-makeindex-opts":[],"latex-tlmgr-opts":[],"latex-input-paths":[],"latex-output-dir":null,"link-external-icon":false,"link-external-newwindow":false,"self-contained-math":false,"format-resources":[]},"pandoc":{"pdf-engine":"lualatex","standalone":true,"variables":{"graphics":true,"tables":true},"default-image-extension":"pdf","to":"pdf","toc":false,"number-sections":false,"output-file":"ECN100B_PS7_solutions.pdf"},"language":{"toc-title-document":"Table of contents","toc-title-website":"On this page","related-formats-title":"Other Formats","related-notebooks-title":"Notebooks","source-notebooks-prefix":"Source","other-links-title":"Other Links","code-links-title":"Code Links","launch-dev-container-title":"Launch Dev Container","launch-binder-title":"Launch Binder","article-notebook-label":"Article Notebook","notebook-preview-download":"Download Notebook","notebook-preview-download-src":"Download Source","notebook-preview-back":"Back to Article","manuscript-meca-bundle":"MECA Bundle","section-title-abstract":"Abstract","section-title-appendices":"Appendices","section-title-footnotes":"Footnotes","section-title-references":"References","section-title-reuse":"Reuse","section-title-copyright":"Copyright","section-title-citation":"Citation","appendix-attribution-cite-as":"For attribution, please cite this work as:","appendix-attribution-bibtex":"BibTeX citation:","appendix-view-license":"View License","title-block-author-single":"Author","title-block-author-plural":"Authors","title-block-affiliation-single":"Affiliation","title-block-affiliation-plural":"Affiliations","title-block-published":"Published","title-block-modified":"Modified","title-block-keywords":"Keywords","callout-tip-title":"Tip","callout-note-title":"Note","callout-warning-title":"Warning","callout-important-title":"Important","callout-caution-title":"Caution","code-summary":"Code","code-tools-menu-caption":"Code","code-tools-show-all-code":"Show All Code","code-tools-hide-all-code":"Hide All Code","code-tools-view-source":"View Source","code-tools-source-code":"Source Code","tools-share":"Share","tools-download":"Download","code-line":"Line","code-lines":"Lines","copy-button-tooltip":"Copy to Clipboard","copy-button-tooltip-success":"Copied!","repo-action-links-edit":"Edit this page","repo-action-links-source":"View source","repo-action-links-issue":"Report an issue","back-to-top":"Back to top","search-no-results-text":"No results","search-matching-documents-text":"matching documents","search-copy-link-title":"Copy link to search","search-hide-matches-text":"Hide additional matches","search-more-match-text":"more match in this document","search-more-matches-text":"more matches in this document","search-clear-button-title":"Clear","search-text-placeholder":"","search-detached-cancel-button-title":"Cancel","search-submit-button-title":"Submit","search-label":"Search","toggle-section":"Toggle section","toggle-sidebar":"Toggle sidebar navigation","toggle-dark-mode":"Toggle dark mode","toggle-reader-mode":"Toggle reader mode","toggle-navigation":"Toggle navigation","crossref-fig-title":"Figure","crossref-tbl-title":"Table","crossref-lst-title":"Listing","crossref-thm-title":"Theorem","crossref-lem-title":"Lemma","crossref-cor-title":"Corollary","crossref-prp-title":"Proposition","crossref-cnj-title":"Conjecture","crossref-def-title":"Definition","crossref-exm-title":"Example","crossref-exr-title":"Exercise","crossref-ch-prefix":"Chapter","crossref-apx-prefix":"Appendix","crossref-sec-prefix":"Section","crossref-eq-prefix":"Equation","crossref-lof-title":"List of Figures","crossref-lot-title":"List of Tables","crossref-lol-title":"List of Listings","environment-proof-title":"Proof","environment-remark-title":"Remark","environment-solution-title":"Solution","listing-page-order-by":"Order By","listing-page-order-by-default":"Default","listing-page-order-by-date-asc":"Oldest","listing-page-order-by-date-desc":"Newest","listing-page-order-by-number-desc":"High to Low","listing-page-order-by-number-asc":"Low to High","listing-page-field-date":"Date","listing-page-field-title":"Title","listing-page-field-description":"Description","listing-page-field-author":"Author","listing-page-field-filename":"File Name","listing-page-field-filemodified":"Modified","listing-page-field-subtitle":"Subtitle","listing-page-field-readingtime":"Reading Time","listing-page-field-wordcount":"Word Count","listing-page-field-categories":"Categories","listing-page-minutes-compact":"{0} min","listing-page-category-all":"All","listing-page-no-matches":"No matching items","listing-page-words":"{0} words","listing-page-filter":"Filter","draft":"Draft"},"metadata":{"block-headings":true,"documentclass":"article","geometry":["margin=1in"],"fontsize":"11pt","linestretch":1.1,"colorlinks":true,"linkcolor":"blue","urlcolor":"blue","citecolor":"blue"},"extensions":{"book":{"selfContainedOutput":true}}}},"projectFormats":["html","pdf"]}