{"title":"Problem Set 6 - Solutions","markdown":{"yaml":{"title":"Problem Set 6 - Solutions","subtitle":"Economics 100B - Intermediate Microeconomic Theory\nProf. Muehlegger\n","author":"Prof. Muehlegger","format":{"pdf":"default","html":"default"}},"headingText":"Question 1: Negative Externalities","containsRefs":false,"markdown":"\n\n\nA perfectly competitive industry produces a good with inverse demand curve P = 200 – Q and inverse\nsupply curve of P = 20 + Q.\n\nIn addition, the production of the good imposes costs on a neighboring town where marginal external costs\nare given by P = Q.\n\n(a) What is the competitive equilibrium?\n\nThe competitive equilibrium is where the supply curve intersects the demand curve. Setting $200 - Q = 20 + Q$ and solving for $Q$ gives $Q = 90$. Substituting $Q = 90$ into the demand equation gives $P = 110$.\n\nSo, the competitive equilibrium is at price P = 110 and quantity Q = 90.\n\n(b) What is the welfare maximizing level of output?\n\nThe welfare maximizing level of output is where the marginal social cost (MSC) equals demand. The MSC\nis the sum of the marginal private cost (MPC) and the marginal external cost (MEC).\n\nIn this case, MPC is given by the supply curve (P = 20 + Q) and MEC is given by P = Q.\n\nSo, MSC = MPC + MEC = 20 + 2Q.\n\nSetting this equal to the demand curve (P = 200 - Q) and solving for Q gives Q = 60. Substituting Q = 60\ninto the demand equation gives P = 140.\n\nSo, the welfare maximizing output is at price P = 140 and quantity Q = 60.\n\n(c) Draw the relevant graph, clearly labeling the inverse demand curve, marginal private cost curve,\nmarginal social cost curve, the competitive equilibrium, the welfare maximizing outcome and the\ndeadweight loss in the unregulated market.\n                                     MSC\n                                                     MPC\n\n                                                      D\n\n(d) Calculate the amount of deadweight loss.\n\nIn this case, the area is given by the red triangle above.\n\nThe base is (90 – 60) = 30.\n\nThe height is given by the difference between the MSC and MPC both evaluated at Q = 90. The height is\ngiven by (200 – 110) = 90\n\nThus, DWL = \\frac{1}{2} * 30 * 90 = 1350.\n\n(e) What is the welfare-maximizing Pigouvian tax?\n\nThe welfare-maximizing Pigouvian tax is equal to marginal external costs at the welfare maximizing\nquantity. In this case, marginal external costs at Q=60 is given P = Q = 60.\n\nThus, the optimal Pigouvian tax is $60.\n\n(f) Draw the relevant graph for part (e), clearly labeling the inverse demand curve, marginal private\ncost curve, marginal social cost curve, and show how the relevant curve will shift once the Pigouvian\ntax in part (e) is enacted.\n                                                     MPC + tax\n                                   MSC\n                                                   MPC\n\n                                                   D\n\n(g) Now, suppose that the firm is produced by a monopolist rather than firms in a perfectly\ncompetitive industry. How much will the monopolist choose to produce?\n\nThe monopolist will maximize profits at the quantity where MR = MPC.\n\nThe monopolist’s MR is given by MR = 200 – 2Q.\n\nSetting this equal to MPC, we have 200 – 2Q = 20 + Q -> 180 = 3Q -> Q = 60.\n\n(h) What would be the optimal tax to levy on the monopolist if the government wanted to maximize\nwelfare? Briefly explain why your answer to part (h) is different than your answer to part (e).\n\nInterestingly, in this case, the amount the monopoly chooses to produce is exactly the same as the welfare-\nmaximizing quantity. Thus, no Pigouvian tax is necessary. The monopolist, by maximizing private profits,\ninadvertently maximizes welfare! This highlights that the incentives for the welfare maximizing policy-\nmaker to reduce output when negative externalities exist align with the incentives for the monopolist to\nreduce output to maximize profits. Although not always true that it works out exactly, in this case, it does\nand the monopolist wants to cut output just as much as the policymaker would want to reduce output.\n\n## Question 2: Public Goods\n\nThe city of Davis operates a public pool during the summer months and can choose how many hours to\noperate the pool. Suppose that it costs $16 per hour to keep the pool open.\n\nAssume that the public pool is free to enter and can easily accommodate all 11 residents.\n\n    -    Suppose there are eleven residents in Davis during August.\n\n    -    The first resident is a professor with kids who has a very high valuation pool hours in the summer.\n         His / her demand for pool hours per day is given by P = 20 - H\n    -    The other ten residents are students, who have lower valuations for summer pool hours.     His / her\n         demand for pool hours per day is given by P = 2 – (\\frac{1}{10})*H\n\n(a) Although in this case, we are assuming that a public pool is free to enter and can easily accommodate all\n11 residents, explain whether in practice a public pool is rivalrous and/or excludable.\n\nA public pool (at least for relatively low levels of attendance) is non-rivalrous. Additional swimmers don’t\nimpact a person’s utility of swimming, until of course the pool is packed. But, whether a public pool is\nexcludable or not depends on whether people can be prevented from using the public pool. For instance,\nthe city pools in Davis have fences around them and you have to enter through a gate where they make you\npay for admission. This is an example of a public pool that is excludable. But, a pool in the middle of an\napartment complex may not be excludable if there’s no fence / guard / gate that can prevent people from\nusing it. If you have a party and 40 of your friends want to jump in the pool, and there’s nothing the\ncomplex can do to stop them, the pool is non-excludable.\n\n(b) If the pool is financed through donations, will the pool be open? How long will it be open? Who will\npay? And who will go to the pool?\n\nIf the pool is financed through donations, only the professor contributes as only the professor has a\nvaluation for pool time greater than the $16/hour. The professor contributes up until the marginal benefit is\nequal to the cost of an additional hour. This happens at 4 hours of pool time. The other residents free-ride\non the professor’s payment.\n\n(c) Draw the diagram illustrating the outcomes in part (b).\n\n       32\n\n(d) What is the surplus generated from the pool in part (b)?\n\nSee the red region in the left panel of (f). The area under SDC but above MC reflects the surplus enjoyed\nby the 11 residents if the city provides 4 hours of pool time per day.\n\nSurplus is equal to the area of the red trapezoid. You can calculate this using the formula for a trapezoid\n(b*average height) = (36 - 16)*4 = 20 * 4 = 80 or by calculating the area of the triangle and rectangle\nseparately = 8*\\frac{4}{2} + 16*4 = 16 + 64 = 80.\n\n(e) Now, assume that the city of Davis finances the pool through taxes. How many hours should the pool\nbe open to maximize welfare?\n\nThe city calculates the social demand function by vertically summing the demand curves. The social\ndemand curve is given by P = 20 – H + 10*(2-(\\frac{1}{10})H) = 40 – 2H. In this case, welfare is maximized\nwhere the social demand curve crosses the marginal cost of additional pool hours.\n\nSetting SDC equal to MC, we have 40 – 2H = 16 -> H = 12. The pool stays open 12 hours per day.\n\n(f) Draw the diagram illustrating the outcomes in part (e).\n\n(g) What is the surplus generated from the pool in part (e)?\n\nSee the orange region in the right panel of (f). The area under SDC but above MC reflects the surplus\nenjoyed by the 11 residents if the city provides 12 hours of pool time per day.\n\nSurplus is equal to (40 – 16)*\\frac{12}{2} = 24 * 6 = 144.\n\n(h) What is the deadweight loss in part (b)?\n\nThe deadweight loss is the difference between the surplus when the good is provided by the city and when\nthe good is privately provided Here, the deadweight loss in part (b) is equal to 144 – 80 = 64.\n\n\n\n\n\n","srcMarkdownNoYaml":"\n\n## Question 1: Negative Externalities\n\nA perfectly competitive industry produces a good with inverse demand curve P = 200 – Q and inverse\nsupply curve of P = 20 + Q.\n\nIn addition, the production of the good imposes costs on a neighboring town where marginal external costs\nare given by P = Q.\n\n(a) What is the competitive equilibrium?\n\nThe competitive equilibrium is where the supply curve intersects the demand curve. Setting $200 - Q = 20 + Q$ and solving for $Q$ gives $Q = 90$. Substituting $Q = 90$ into the demand equation gives $P = 110$.\n\nSo, the competitive equilibrium is at price P = 110 and quantity Q = 90.\n\n(b) What is the welfare maximizing level of output?\n\nThe welfare maximizing level of output is where the marginal social cost (MSC) equals demand. The MSC\nis the sum of the marginal private cost (MPC) and the marginal external cost (MEC).\n\nIn this case, MPC is given by the supply curve (P = 20 + Q) and MEC is given by P = Q.\n\nSo, MSC = MPC + MEC = 20 + 2Q.\n\nSetting this equal to the demand curve (P = 200 - Q) and solving for Q gives Q = 60. Substituting Q = 60\ninto the demand equation gives P = 140.\n\nSo, the welfare maximizing output is at price P = 140 and quantity Q = 60.\n\n(c) Draw the relevant graph, clearly labeling the inverse demand curve, marginal private cost curve,\nmarginal social cost curve, the competitive equilibrium, the welfare maximizing outcome and the\ndeadweight loss in the unregulated market.\n                                     MSC\n                                                     MPC\n\n                                                      D\n\n(d) Calculate the amount of deadweight loss.\n\nIn this case, the area is given by the red triangle above.\n\nThe base is (90 – 60) = 30.\n\nThe height is given by the difference between the MSC and MPC both evaluated at Q = 90. The height is\ngiven by (200 – 110) = 90\n\nThus, DWL = \\frac{1}{2} * 30 * 90 = 1350.\n\n(e) What is the welfare-maximizing Pigouvian tax?\n\nThe welfare-maximizing Pigouvian tax is equal to marginal external costs at the welfare maximizing\nquantity. In this case, marginal external costs at Q=60 is given P = Q = 60.\n\nThus, the optimal Pigouvian tax is $60.\n\n(f) Draw the relevant graph for part (e), clearly labeling the inverse demand curve, marginal private\ncost curve, marginal social cost curve, and show how the relevant curve will shift once the Pigouvian\ntax in part (e) is enacted.\n                                                     MPC + tax\n                                   MSC\n                                                   MPC\n\n                                                   D\n\n(g) Now, suppose that the firm is produced by a monopolist rather than firms in a perfectly\ncompetitive industry. How much will the monopolist choose to produce?\n\nThe monopolist will maximize profits at the quantity where MR = MPC.\n\nThe monopolist’s MR is given by MR = 200 – 2Q.\n\nSetting this equal to MPC, we have 200 – 2Q = 20 + Q -> 180 = 3Q -> Q = 60.\n\n(h) What would be the optimal tax to levy on the monopolist if the government wanted to maximize\nwelfare? Briefly explain why your answer to part (h) is different than your answer to part (e).\n\nInterestingly, in this case, the amount the monopoly chooses to produce is exactly the same as the welfare-\nmaximizing quantity. Thus, no Pigouvian tax is necessary. The monopolist, by maximizing private profits,\ninadvertently maximizes welfare! This highlights that the incentives for the welfare maximizing policy-\nmaker to reduce output when negative externalities exist align with the incentives for the monopolist to\nreduce output to maximize profits. Although not always true that it works out exactly, in this case, it does\nand the monopolist wants to cut output just as much as the policymaker would want to reduce output.\n\n## Question 2: Public Goods\n\nThe city of Davis operates a public pool during the summer months and can choose how many hours to\noperate the pool. Suppose that it costs $16 per hour to keep the pool open.\n\nAssume that the public pool is free to enter and can easily accommodate all 11 residents.\n\n    -    Suppose there are eleven residents in Davis during August.\n\n    -    The first resident is a professor with kids who has a very high valuation pool hours in the summer.\n         His / her demand for pool hours per day is given by P = 20 - H\n    -    The other ten residents are students, who have lower valuations for summer pool hours.     His / her\n         demand for pool hours per day is given by P = 2 – (\\frac{1}{10})*H\n\n(a) Although in this case, we are assuming that a public pool is free to enter and can easily accommodate all\n11 residents, explain whether in practice a public pool is rivalrous and/or excludable.\n\nA public pool (at least for relatively low levels of attendance) is non-rivalrous. Additional swimmers don’t\nimpact a person’s utility of swimming, until of course the pool is packed. But, whether a public pool is\nexcludable or not depends on whether people can be prevented from using the public pool. For instance,\nthe city pools in Davis have fences around them and you have to enter through a gate where they make you\npay for admission. This is an example of a public pool that is excludable. But, a pool in the middle of an\napartment complex may not be excludable if there’s no fence / guard / gate that can prevent people from\nusing it. If you have a party and 40 of your friends want to jump in the pool, and there’s nothing the\ncomplex can do to stop them, the pool is non-excludable.\n\n(b) If the pool is financed through donations, will the pool be open? How long will it be open? Who will\npay? And who will go to the pool?\n\nIf the pool is financed through donations, only the professor contributes as only the professor has a\nvaluation for pool time greater than the $16/hour. The professor contributes up until the marginal benefit is\nequal to the cost of an additional hour. This happens at 4 hours of pool time. The other residents free-ride\non the professor’s payment.\n\n(c) Draw the diagram illustrating the outcomes in part (b).\n\n       32\n\n(d) What is the surplus generated from the pool in part (b)?\n\nSee the red region in the left panel of (f). The area under SDC but above MC reflects the surplus enjoyed\nby the 11 residents if the city provides 4 hours of pool time per day.\n\nSurplus is equal to the area of the red trapezoid. You can calculate this using the formula for a trapezoid\n(b*average height) = (36 - 16)*4 = 20 * 4 = 80 or by calculating the area of the triangle and rectangle\nseparately = 8*\\frac{4}{2} + 16*4 = 16 + 64 = 80.\n\n(e) Now, assume that the city of Davis finances the pool through taxes. How many hours should the pool\nbe open to maximize welfare?\n\nThe city calculates the social demand function by vertically summing the demand curves. The social\ndemand curve is given by P = 20 – H + 10*(2-(\\frac{1}{10})H) = 40 – 2H. In this case, welfare is maximized\nwhere the social demand curve crosses the marginal cost of additional pool hours.\n\nSetting SDC equal to MC, we have 40 – 2H = 16 -> H = 12. The pool stays open 12 hours per day.\n\n(f) Draw the diagram illustrating the outcomes in part (e).\n\n(g) What is the surplus generated from the pool in part (e)?\n\nSee the orange region in the right panel of (f). The area under SDC but above MC reflects the surplus\nenjoyed by the 11 residents if the city provides 12 hours of pool time per day.\n\nSurplus is equal to (40 – 16)*\\frac{12}{2} = 24 * 6 = 144.\n\n(h) What is the deadweight loss in part (b)?\n\nThe deadweight loss is the difference between the surplus when the good is provided by the city and when\nthe good is privately provided Here, the deadweight loss in part (b) is equal to 144 – 80 = 64.\n\n\n\n\n\n"},"formats":{"html":{"identifier":{"display-name":"HTML","target-format":"html","base-format":"html"},"execute":{"fig-width":7,"fig-height":5,"fig-format":"retina","fig-dpi":96,"df-print":"default","error":false,"eval":true,"cache":false,"freeze":false,"echo":false,"output":true,"warning":false,"include":true,"keep-md":false,"keep-ipynb":false,"ipynb":null,"enabled":null,"daemon":null,"daemon-restart":false,"debug":false,"ipynb-filters":[],"ipynb-shell-interactivity":null,"plotly-connected":true,"message":false,"engine":"markdown"},"render":{"keep-tex":false,"keep-typ":false,"keep-source":false,"keep-hidden":false,"prefer-html":false,"output-divs":true,"output-ext":"html","fig-align":"default","fig-pos":null,"fig-env":null,"code-fold":true,"code-overflow":"scroll","code-link":false,"code-line-numbers":false,"code-tools":false,"tbl-colwidths":"auto","merge-includes":true,"inline-includes":false,"preserve-yaml":false,"latex-auto-mk":true,"latex-auto-install":true,"latex-clean":true,"latex-min-runs":1,"latex-max-runs":10,"latex-makeindex":"makeindex","latex-makeindex-opts":[],"latex-tlmgr-opts":[],"latex-input-paths":[],"latex-output-dir":null,"link-external-icon":false,"link-external-newwindow":true,"self-contained-math":false,"format-resources":[],"notebook-links":true},"pandoc":{"standalone":true,"wrap":"none","default-image-extension":"png","to":"html","toc":false,"toc-depth":3,"number-sections":false,"embed-resources":true,"self-contained":true,"html-math-method":"katex","output-file":"ECN100B_PS6_solutions.html"},"language":{"toc-title-document":"Table of contents","toc-title-website":"On this page","related-formats-title":"Other Formats","related-notebooks-title":"Notebooks","source-notebooks-prefix":"Source","other-links-title":"Other Links","code-links-title":"Code Links","launch-dev-container-title":"Launch Dev Container","launch-binder-title":"Launch Binder","article-notebook-label":"Article Notebook","notebook-preview-download":"Download Notebook","notebook-preview-download-src":"Download Source","notebook-preview-back":"Back to Article","manuscript-meca-bundle":"MECA Bundle","section-title-abstract":"Abstract","section-title-appendices":"Appendices","section-title-footnotes":"Footnotes","section-title-references":"References","section-title-reuse":"Reuse","section-title-copyright":"Copyright","section-title-citation":"Citation","appendix-attribution-cite-as":"For attribution, please cite this work as:","appendix-attribution-bibtex":"BibTeX citation:","appendix-view-license":"View License","title-block-author-single":"Author","title-block-author-plural":"Authors","title-block-affiliation-single":"Affiliation","title-block-affiliation-plural":"Affiliations","title-block-published":"Published","title-block-modified":"Modified","title-block-keywords":"Keywords","callout-tip-title":"Tip","callout-note-title":"Note","callout-warning-title":"Warning","callout-important-title":"Important","callout-caution-title":"Caution","code-summary":"Code","code-tools-menu-caption":"Code","code-tools-show-all-code":"Show All Code","code-tools-hide-all-code":"Hide All Code","code-tools-view-source":"View Source","code-tools-source-code":"Source Code","tools-share":"Share","tools-download":"Download","code-line":"Line","code-lines":"Lines","copy-button-tooltip":"Copy to Clipboard","copy-button-tooltip-success":"Copied!","repo-action-links-edit":"Edit this page","repo-action-links-source":"View source","repo-action-links-issue":"Report an issue","back-to-top":"Back to top","search-no-results-text":"No results","search-matching-documents-text":"matching documents","search-copy-link-title":"Copy link to search","search-hide-matches-text":"Hide additional matches","search-more-match-text":"more match in this document","search-more-matches-text":"more matches in this document","search-clear-button-title":"Clear","search-text-placeholder":"","search-detached-cancel-button-title":"Cancel","search-submit-button-title":"Submit","search-label":"Search","toggle-section":"Toggle section","toggle-sidebar":"Toggle sidebar navigation","toggle-dark-mode":"Toggle dark mode","toggle-reader-mode":"Toggle reader mode","toggle-navigation":"Toggle navigation","crossref-fig-title":"Figure","crossref-tbl-title":"Table","crossref-lst-title":"Listing","crossref-thm-title":"Theorem","crossref-lem-title":"Lemma","crossref-cor-title":"Corollary","crossref-prp-title":"Proposition","crossref-cnj-title":"Conjecture","crossref-def-title":"Definition","crossref-exm-title":"Example","crossref-exr-title":"Exercise","crossref-ch-prefix":"Chapter","crossref-apx-prefix":"Appendix","crossref-sec-prefix":"Section","crossref-eq-prefix":"Equation","crossref-lof-title":"List of Figures","crossref-lot-title":"List of Tables","crossref-lol-title":"List of Listings","environment-proof-title":"Proof","environment-remark-title":"Remark","environment-solution-title":"Solution","listing-page-order-by":"Order By","listing-page-order-by-default":"Default","listing-page-order-by-date-asc":"Oldest","listing-page-order-by-date-desc":"Newest","listing-page-order-by-number-desc":"High to Low","listing-page-order-by-number-asc":"Low to High","listing-page-field-date":"Date","listing-page-field-title":"Title","listing-page-field-description":"Description","listing-page-field-author":"Author","listing-page-field-filename":"File Name","listing-page-field-filemodified":"Modified","listing-page-field-subtitle":"Subtitle","listing-page-field-readingtime":"Reading Time","listing-page-field-wordcount":"Word Count","listing-page-field-categories":"Categories","listing-page-minutes-compact":"{0} min","listing-page-category-all":"All","listing-page-no-matches":"No matching items","listing-page-words":"{0} words","listing-page-filter":"Filter","draft":"Draft"},"metadata":{"lang":"en","fig-responsive":true,"quarto-version":"1.8.27","toc-location":"right","anchor-sections":true,"smooth-scroll":false,"theme":"cosmo","fig-cap-location":"bottom","code-copy":true,"citations-hover":false,"crossref":{"fig-title":"Figure","tbl-title":"Table","eq-title":"Equation"}},"extensions":{"book":{"multiFile":true}}},"pdf":{"identifier":{"display-name":"PDF","target-format":"pdf","base-format":"pdf"},"execute":{"fig-width":5.5,"fig-height":3.5,"fig-format":"pdf","fig-dpi":300,"df-print":"default","error":false,"eval":true,"cache":false,"freeze":false,"echo":false,"output":true,"warning":false,"include":true,"keep-md":false,"keep-ipynb":false,"ipynb":null,"enabled":null,"daemon":null,"daemon-restart":false,"debug":false,"ipynb-filters":[],"ipynb-shell-interactivity":null,"plotly-connected":true,"message":false,"engine":"markdown"},"render":{"keep-tex":false,"keep-typ":false,"keep-source":false,"keep-hidden":false,"prefer-html":false,"output-divs":true,"output-ext":"pdf","fig-align":"default","fig-pos":"htbp","fig-env":null,"code-fold":"none","code-overflow":"scroll","code-link":false,"code-line-numbers":false,"code-tools":false,"tbl-colwidths":true,"merge-includes":true,"inline-includes":false,"preserve-yaml":false,"latex-auto-mk":true,"latex-auto-install":true,"latex-clean":true,"latex-min-runs":1,"latex-max-runs":10,"latex-makeindex":"makeindex","latex-makeindex-opts":[],"latex-tlmgr-opts":[],"latex-input-paths":[],"latex-output-dir":null,"link-external-icon":false,"link-external-newwindow":false,"self-contained-math":false,"format-resources":[]},"pandoc":{"pdf-engine":"lualatex","standalone":true,"variables":{"graphics":true,"tables":true},"default-image-extension":"pdf","to":"pdf","toc":false,"number-sections":false,"output-file":"ECN100B_PS6_solutions.pdf"},"language":{"toc-title-document":"Table of contents","toc-title-website":"On this page","related-formats-title":"Other Formats","related-notebooks-title":"Notebooks","source-notebooks-prefix":"Source","other-links-title":"Other Links","code-links-title":"Code Links","launch-dev-container-title":"Launch Dev Container","launch-binder-title":"Launch Binder","article-notebook-label":"Article Notebook","notebook-preview-download":"Download Notebook","notebook-preview-download-src":"Download Source","notebook-preview-back":"Back to Article","manuscript-meca-bundle":"MECA Bundle","section-title-abstract":"Abstract","section-title-appendices":"Appendices","section-title-footnotes":"Footnotes","section-title-references":"References","section-title-reuse":"Reuse","section-title-copyright":"Copyright","section-title-citation":"Citation","appendix-attribution-cite-as":"For attribution, please cite this work as:","appendix-attribution-bibtex":"BibTeX citation:","appendix-view-license":"View License","title-block-author-single":"Author","title-block-author-plural":"Authors","title-block-affiliation-single":"Affiliation","title-block-affiliation-plural":"Affiliations","title-block-published":"Published","title-block-modified":"Modified","title-block-keywords":"Keywords","callout-tip-title":"Tip","callout-note-title":"Note","callout-warning-title":"Warning","callout-important-title":"Important","callout-caution-title":"Caution","code-summary":"Code","code-tools-menu-caption":"Code","code-tools-show-all-code":"Show All Code","code-tools-hide-all-code":"Hide All Code","code-tools-view-source":"View Source","code-tools-source-code":"Source Code","tools-share":"Share","tools-download":"Download","code-line":"Line","code-lines":"Lines","copy-button-tooltip":"Copy to Clipboard","copy-button-tooltip-success":"Copied!","repo-action-links-edit":"Edit this page","repo-action-links-source":"View source","repo-action-links-issue":"Report an issue","back-to-top":"Back to top","search-no-results-text":"No results","search-matching-documents-text":"matching documents","search-copy-link-title":"Copy link to search","search-hide-matches-text":"Hide additional matches","search-more-match-text":"more match in this document","search-more-matches-text":"more matches in this document","search-clear-button-title":"Clear","search-text-placeholder":"","search-detached-cancel-button-title":"Cancel","search-submit-button-title":"Submit","search-label":"Search","toggle-section":"Toggle section","toggle-sidebar":"Toggle sidebar navigation","toggle-dark-mode":"Toggle dark mode","toggle-reader-mode":"Toggle reader mode","toggle-navigation":"Toggle navigation","crossref-fig-title":"Figure","crossref-tbl-title":"Table","crossref-lst-title":"Listing","crossref-thm-title":"Theorem","crossref-lem-title":"Lemma","crossref-cor-title":"Corollary","crossref-prp-title":"Proposition","crossref-cnj-title":"Conjecture","crossref-def-title":"Definition","crossref-exm-title":"Example","crossref-exr-title":"Exercise","crossref-ch-prefix":"Chapter","crossref-apx-prefix":"Appendix","crossref-sec-prefix":"Section","crossref-eq-prefix":"Equation","crossref-lof-title":"List of Figures","crossref-lot-title":"List of Tables","crossref-lol-title":"List of Listings","environment-proof-title":"Proof","environment-remark-title":"Remark","environment-solution-title":"Solution","listing-page-order-by":"Order By","listing-page-order-by-default":"Default","listing-page-order-by-date-asc":"Oldest","listing-page-order-by-date-desc":"Newest","listing-page-order-by-number-desc":"High to Low","listing-page-order-by-number-asc":"Low to High","listing-page-field-date":"Date","listing-page-field-title":"Title","listing-page-field-description":"Description","listing-page-field-author":"Author","listing-page-field-filename":"File Name","listing-page-field-filemodified":"Modified","listing-page-field-subtitle":"Subtitle","listing-page-field-readingtime":"Reading Time","listing-page-field-wordcount":"Word Count","listing-page-field-categories":"Categories","listing-page-minutes-compact":"{0} min","listing-page-category-all":"All","listing-page-no-matches":"No matching items","listing-page-words":"{0} words","listing-page-filter":"Filter","draft":"Draft"},"metadata":{"block-headings":true,"documentclass":"article","geometry":["margin=1in"],"fontsize":"11pt","linestretch":1.1,"colorlinks":true,"linkcolor":"blue","urlcolor":"blue","citecolor":"blue"},"extensions":{"book":{"selfContainedOutput":true}}}},"projectFormats":["html","pdf"]}